svg2wkt/__init__.py
svg2wkt-0.1.0.dist-info/METADATA
svg2wkt-0.1.0.dist-info/WHEEL
svg2wkt-0.1.0.dist-info/licenses/LICENSE.txt
svg2wkt-0.1.0.dist-info/RECORD
